{
  "version": "1.0",
  "query_file_checksums": {
    "db/queries/users.sql": "0fec496bff1e53d041b080e9275485ccbdc1b8156767b4a70a0c522aa0715c52"
  },
  "schema_checksum": "171ee2528639fefc00afe1f6aa4bcacbb98359e6d077dab8d08aa3e2e14cd4c7",
  "config_checksum": "2b830583743a1e919dfbb71ac169ec632459c70b9335cd180c7d80a891f75537",
  "query_table_deps": {
    "db/queries/users.sql": [
      "categories",
      "tags",
      "post_tags",
      "user_post_stats",
      "user_activity_summary",
      "subscriptions",
      "users",
      "posts",
      "active_users",
      "orders",
      "media",
      "notifications",
      "active_commenters",
      "users;",
      "post_stats",
      "audit_log",
      "comments"
    ]
  },
  "generated_file_checksums": {
    "flash_gen/users.go": "99e31b1f0f04cb0f9a396b703bb24a48de53cde77c81693b89da4f84afd0b827"
  },
  "last_generation": "2026-06-17T02:20:30.413838991+05:30",
  "OutDir": "flash_gen"
}